{"date":"2026-06-12","price":63409.0,"price_indicators":{"ma200w":62021.66,"pct_above_200w":2.2,"signal_200w":"neutral","ma200d":77883.94,"pct_above_200d":-18.6,"signal_200d":"accumulate","pi_cycle_111d":72180.03,"pi_cycle_350d_2x":184654.07,"pi_cycle_gap_pct":-60.9,"signal_pi_cycle":"distribute","rsi_daily":32.5859914730184,"signal_rsi_d":"accumulate","rsi_weekly":34.67093132436817,"signal_rsi_w":"accumulate","atr_distance":-1.686287375961679,"regime":"Trend","signal_atr":"neutral","vp_position":"below_val","signal_vp":"accumulate"},"sentiment":{"fear_greed":{"value":12,"label":"Extreme Fear","timestamp":"1781222400"},"signal_fear_greed":"accumulate","funding_rate":null,"signal_funding":null,"open_interest_usd":null,"signal_oi":null,"etf_flows":{"date":"2026-06-11","net_inflow_usd":-19026463.759999998,"flow_7d_usd":-3252953659.585,"total_net_assets_usd":79497876550.62064,"cum_net_inflow_usd":53538641260.353,"signal":"neutral"},"signal_etf":"neutral"},"market_structure":{"btc_dominance":56.33725378324422,"signal_btcd":"neutral","altseason":{"score":30,"label":"Leaning BTC","alts_outperforming":8,"total":27},"signal_alts":"neutral"},"mining":{"hashrate_30d_eh":944.17,"hashrate_60d_eh":956.98,"signal":"bear","puell_multiple":0.883,"puell_daily_revenue_usd":28720229,"puell_ma_365d_usd":32516067,"signal_puell":"neutral"},"liquidity":{"usdt_supply_usd":186683677631.93372,"usdc_supply_usd":74827526440.89616,"combined_supply_usd":261511204072.8299,"change_30d_pct":-1.85,"dominance_pct":11.57,"signal":"flat","global_m2_billion_usd":22879.0,"m2_12w_lagged_change_pct":0.9,"m2_current_change_pct":1.8,"signal_global_m2":"neutral"},"on_chain":{"mvrv_z_score":null,"nupl":null,"nupl_30d_change":null,"sopr":null,"signal_mvrv_z":null,"signal_nupl":null,"signal_sopr":null,"cdd_latest":null,"cdd_90d_avg":null,"cdd_90d_change_pct":null,"signal_cvdd":null,"supply_cross_occurred":null,"signal_supply_cross":null},"confluence":{"accumulate_count":5,"distribute_count":1,"neutral_count":8,"phase":"Accumulation","strength":"moderate"}}